{
  "projects": [
    {
      "title": "Dark Premium Portfolio",
      "description": "A one-page premium portfolio running on GitHub Pages with smooth animations and a data-driven projects section.",
      "tags": ["HTML", "CSS", "JS", "GitHub Pages"],
      "repo": "https://github.com/jamdanie/dark-premium-portfolio",
      "live": "https://jamdanie.github.io/dark-premium-portfolio/",
      "featured": true
    },
    {
      "title": "C# JSON Generator",
      "description": "C# tool that generates the site’s projects.json via GitHub Actions (still fully inside GitHub).",
      "tags": ["C#", ".NET", "GitHub Actions"],
      "repo": "https://github.com/jamdanie/dark-premium-portfolio",
      "live": "",
      "featured": false
    }
  ]
}
